README.md
setup.py
telega/__init__.py
telega/client.py
telega/errors.py
telega/tdjson.py
telega.egg-info/PKG-INFO
telega.egg-info/SOURCES.txt
telega.egg-info/dependency_links.txt
telega.egg-info/top_level.txt
telega/td_lib/linux/libtdjson.so.1.4.0