Metadata-Version: 1.2
Name: telega
Version: 1.1.10
Summary: Python Telegram TDLib sync client
Home-page: https://github.com/RusJr/telega
Author: Rus Jr
Author-email: binderrrr@gmail.com
License: MIT
Keywords: telegram telega client tglib
Platform: UNKNOWN
Requires-Python: >=3.5
